README.rst
setup.py
django_abstract_utils/__init__.py
django_abstract_utils.egg-info/PKG-INFO
django_abstract_utils.egg-info/SOURCES.txt
django_abstract_utils.egg-info/dependency_links.txt
django_abstract_utils.egg-info/requires.txt
django_abstract_utils.egg-info/top_level.txt