Metadata-Version: 1.0
Name: django-abstract-utils
Version: 0.0.1
Summary: UNKNOWN
Home-page: https://github.com/IlyaSemenov/django-abstract-utils
Author: Ilya Semenov
Author-email: ilya@semenov.co
License: BSD
Platform: UNKNOWN
